<?xml version="1.0" encoding="UTF-8"?><?mso-infoPathSolution PIVersion="1.0.0.0" href="http://devinfo/sites/sdk/netengdt/NetEngDtSample/Forms/template.xsn" name="urn:schemas-microsoft-com:office:infopath:NETEngDtSample:" language="en-us" solutionVersion="9.4.0.846" productVersion="14.0.0" ?><?mso-application progid="InfoPath.Document"?><esri_sdk_sample xmlns:xsi="http://www.w3.org/2001/XMLSchema-instance" xmlns:xhtml="http://www.w3.org/1999/xhtml" xmlns:my="http://schemas.microsoft.com/office/infopath/2003/myXSD/2008-08-20T22:42:53" xmlns:xd="http://schemas.microsoft.com/office/infopath/2003">
	<title>Browse for Python files</title>
	<purpose>This sample code demonstrates how to create a custom object filter in ArcCatalog and use it through a custom command to select a Python file (*.py). </purpose>
	<development_license>
		<license>
			<name>ArcGIS for Desktop Basic</name>
			<extension></extension>
		</license>
	<license>
									<name>ArcGIS for Desktop Standard</name>
									<extension></extension>
								</license><license>
									<name>ArcGIS for Desktop Advanced</name>
									<extension></extension>
								</license></development_license>
	<deployment_license>
		<license>
			<name>ArcGIS for Desktop Basic</name>
			<extension></extension>
		</license>
	<license>
									<name>ArcGIS for Desktop Standard</name>
									<extension></extension>
								</license><license>
									<name>ArcGIS for Desktop Advanced</name>
									<extension></extension>
								</license></deployment_license>
	<apis>
		<api></api>
	</apis>
	<capabilities>
		<capability></capability>
	</capabilities>
	<min_version>10.0</min_version>
	<min_sp></min_sp>
	<max_version></max_version>
	<max_sp></max_sp>
	<data_paths>
		<data_path></data_path>
	</data_paths>
	<requirements>
		<requires></requires>
	</requirements>
	<file_section>
		<files lang="CSharp">
			<file>
				<filename>CustomCommand.cs</filename>
				<description>Command code for browsing for a file based on the custom filter.</description>
				<viewable_code>true</viewable_code>
			</file>
		<file>
									<filename>CustomFilter.cs</filename>
									<description>Class implements IGxObjectFilter for filtering Python files.</description>
									<viewable_code>true</viewable_code>
								</file><file>
									<filename>Config.esriaddinx</filename>
									<description>Add-in's declarations.</description>
									<viewable_code>true</viewable_code>
								</file><file>
									<filename>Config.Designer.cs</filename>
									<description>Auto generated.</description>
									<viewable_code>true</viewable_code>
								</file></files>
	<files lang="VBNet">
									<file>
										<filename>CustomCommand.vb</filename>
										<description>Command code for browsing for a file based on the custom filter.</description>
										<viewable_code>true</viewable_code>
									</file>
								<file>
									<filename>CustomFilter.vb</filename>
									<description>Class implements IGxObjectFilter for filtering Python files.</description>
									<viewable_code>true</viewable_code>
								</file><file>
									<filename>Config.esriaddinx</filename>
									<description>Add-in's declarations.</description>
									<viewable_code>true</viewable_code>
								</file><file>
									<filename>Config.Designer.vb</filename>
									<description>Auto generated.</description>
									<viewable_code>true</viewable_code>
								</file></files></file_section>
	<how_to_use_section>
		<how_to_use>
			<title></title>
			<how_to_use_steps>
				<step>Start Visual Studio and build the solution.</step><step>Start ArcCatalog.</step><step>Click the Customize menu and select Add-In manager.</step><step>On the Add-Ins tab, there should be CustomGxFilterVBNET or CustomGxFilter_CS. If not, click Customize, Command tab, then click Add from File. </step><step>Navigate to the location of the built solution (that is, CustomGxFilterVBNET.esriAddIn or CustomGxFilter_CS.esriAddIn).</step><step>Install the add-in.</step><step>On the Commands tab, under Categories, make sure Add-In Controls is highlighted. </step><step>Select and drag the button to the existing ArcCatalog toolbar.</step>
			</how_to_use_steps>
		</how_to_use>
	</how_to_use_section>
	<related_topics>
		
	</related_topics>
	<content_area_tags>
		<tag></tag>
	</content_area_tags>
	<indexing_tags>
		<existing_tag></existing_tag>
	</indexing_tags>
	<guid>ed3fe22f-7723-4c86-8dc1-c87572e290f3</guid>
	<content_management>
		<owner>Bobby Pohan</owner>
		<tech_reviewer>Kent Marten</tech_reviewer>
		<status>SDK inclusion completed</status>
		<sdk_inclusion_complete>
			<NET>false</NET>
			<JAVA>false</JAVA>
			<CPP>false</CPP>
			<XO>false</XO>
		</sdk_inclusion_complete>
		<requested_tocs>
			<desktop>false</desktop>
			<engine>false</engine>
			<server>false</server>
			<net_ide_integration>false</net_ide_integration>
			<xo>false</xo>
		</requested_tocs>
		<applied_tocs>
			<desktop>false</desktop>
			<engine>false</engine>
			<server>false</server>
			<net_ide_integration>false</net_ide_integration>
			<xo>false</xo>
		</applied_tocs>
		<langrev_last_updated_date>2010-09-02</langrev_last_updated_date>
		<langrev_last_updated_time>11:42:52</langrev_last_updated_time>
		<last_updated_date>2010-10-11</last_updated_date>
		<last_updated_time>14:55:57</last_updated_time>
	<copyediting>
									<last_copyedit_date>2010-09-10</last_copyedit_date>
									<last_copyedit_time>10:14:54</last_copyedit_time>
									<copyeditor>mine3384</copyeditor>
								</copyediting><edits>
									<editing_section>
										<editor_name>mine3384</editor_name>
										<edit_date>2010-09-10</edit_date>
										<edit_time>10:14:58</edit_time>
										<edit_notes><ul xmlns="http://www.w3.org/1999/xhtml" style="MARGIN-TOP: 0px; MARGIN-BOTTOM: 0px" type="disc">
<li style="PADDING-RIGHT: 0in; MARGIN-TOP: 0in; PADDING-LEFT: 0in; FONT-SIZE: 12pt; MARGIN-BOTTOM: 0pt"><font face="Times New Roman">Edited according to our style guidelines: <a href="http://devinfo/sites/sdk/shared%20documents/styleguide.aspx">http://devinfo/sites/sdk/shared%20documents/styleguide.aspx</a>.</font></li>
<li style="PADDING-RIGHT: 0in; MARGIN-TOP: 0in; PADDING-LEFT: 0in; FONT-SIZE: 12pt; MARGIN-BOTTOM: 0pt"><font face="Times New Roman">SDK inclusion requested.</font></li>
<li style="PADDING-RIGHT: 0in; MARGIN-TOP: 0in; PADDING-LEFT: 0in; FONT-SIZE: 12pt; MARGIN-BOTTOM: 0pt"><font face="Times New Roman">Changed the link for "How to register COM components" to the GUID (8ec382ff-a019-4f22-8057-c5b075c99b95). Removed the path, <a href="http://help.arcgis.com/en/sdk/10.0/arcobjects_net/conceptualhelp/index.html#//0001000002pv000000">http://help.arcgis.com/en/sdk/10.0/arcobjects_net/conceptualhelp/index.html#//0001000002pv000000</a>.</font></li>
<ul style="MARGIN-TOP: 0px; MARGIN-BOTTOM: 0px" type="disc">
<li style="PADDING-RIGHT: 0in; MARGIN-TOP: 0in; PADDING-LEFT: 0in; FONT-SIZE: 12pt; MARGIN-BOTTOM: 0pt"><font face="Times New Roman">Do not use the URL that is on the Web site. Use the correct GUID for SDK topics. To find the GUID, use the SDK Content Finder located on our SDK team site under the Utilities column on the left (<a href="http://devinfo/sites/sdk/default.aspx">http://devinfo/sites/sdk/default.aspx</a>). </font></li>
<li style="PADDING-RIGHT: 0in; MARGIN-TOP: 0in; PADDING-LEFT: 0in; FONT-SIZE: 12pt; MARGIN-BOTTOM: 0pt"><font face="Times New Roman">For linking conventions, see the InfoPath guide (<a href="http://devinfo/sites/sdk/shared%20documents/infopathGuide.aspx#Hyperlink_syntax_conventions">http://devinfo/sites/sdk/shared%20documents/infopathGuide.aspx#Hyperlink_syntax_conventions</a>).</font></li></ul></ul></edit_notes>
									</editing_section>
								</edits></content_management>
	<current_user>kent4716</current_user>
	<sdk>NETEngDt</sdk>
	<doc_type>Sample</doc_type>
</esri_sdk_sample>